django_hmac_authentication/__init__.py
django_hmac_authentication/admin.py
django_hmac_authentication/apps.py
django_hmac_authentication/authentication.py
django_hmac_authentication/checks.py
django_hmac_authentication/client_utils.py
django_hmac_authentication/exceptions.py
django_hmac_authentication/models.py
django_hmac_authentication/serializers.py
django_hmac_authentication/server_utils.py
django_hmac_authentication/settings.py
django_hmac_authentication/signals.py
django_hmac_authentication/throttling.py
django_hmac_authentication/views.py
django_hmac_authentication/management/__init__.py
django_hmac_authentication/management/commands/__init__.py
django_hmac_authentication/management/commands/create_hmac_for_user.py
django_hmac_authentication/migrations/0001_initial.py
django_hmac_authentication/migrations/0002_apihmackey_failed_attempts.py
django_hmac_authentication/migrations/0003_apihmackey_expires_at.py
django_hmac_authentication/migrations/0004_apihmackey_throttle_rate.py
django_hmac_authentication/migrations/0005_alter_apihmackey_throttle_rate.py
django_hmac_authentication/migrations/0006_apihmackey_cipher_algorithm.py
django_hmac_authentication/migrations/0007_apihmackey_test_mode.py
django_hmac_authentication/migrations/__init__.py
django_hmac_authentication-5.0.2.dist-info/licenses/LICENSE
django_hmac_authentication-5.0.2.dist-info/METADATA
django_hmac_authentication-5.0.2.dist-info/WHEEL
django_hmac_authentication-5.0.2.dist-info/top_level.txt
django_hmac_authentication-5.0.2.dist-info/RECORD
