Metadata-Version: 2.4
Name: django_hmac_authentication
Version: 5.0.2
Summary: Django HMAC authentication using shared secret
Author-email: "Harisankar Krishna Swamy @ Vevde" <harisankar.krishna@outlook.com>
Project-URL: Homepage, https://github.com/harisankar-krishna-swamy/django_hmac_authentication
Classifier: Programming Language :: Python :: 3
Classifier: License :: OSI Approved :: Apache Software License
Classifier: Operating System :: OS Independent
Requires-Python: >=3.9.2
License-File: LICENSE
Requires-Dist: Django>=3.2.18
Requires-Dist: djangorestframework>=3.12.4
Requires-Dist: cryptography>=3.4.8
Requires-Dist: vevde-security-utils>=2.0.0
Dynamic: license-file
